{
  "repos": [
    {
      "id": "T4DVt1OZzf",
      "name": "Rohan",
      "description": "code",
      "owner": "guest",
      "visibility": "public",
      "createdAt": "2025-08-15T09:17:08.017Z",
      "files": [
        {
          "id": "XkrfeEAQpY",
          "name": "eg.txt",
          "content": "this is inside txt file",
          "updatedAt": "2025-08-15T09:17:56.366Z"
        },
        {
          "id": "pmjAtaa6Nn",
          "name": "rohan.js",
          "content": "<div class=\"mono\"><%= f.name %></div>",
          "updatedAt": "2025-08-15T09:18:32.852Z"
        }
      ],
      "commits": [
        {
          "id": "2GBXYDSg",
          "message": "Initial commit",
          "timestamp": "2025-08-15T09:17:08.017Z",
          "filesSnapshot": []
        },
        {
          "id": "s7uUN94O",
          "message": "testing",
          "timestamp": "2025-08-15T09:17:56.366Z",
          "filesSnapshot": [
            {
              "id": "XkrfeEAQpY",
              "name": "eg.txt",
              "content": "this is inside txt file",
              "updatedAt": "2025-08-15T09:17:56.366Z"
            }
          ]
        },
        {
          "id": "sD1nSTAW",
          "message": "create js file",
          "timestamp": "2025-08-15T09:18:32.852Z",
          "filesSnapshot": [
            {
              "id": "XkrfeEAQpY",
              "name": "eg.txt",
              "content": "this is inside txt file",
              "updatedAt": "2025-08-15T09:17:56.366Z"
            },
            {
              "id": "pmjAtaa6Nn",
              "name": "rohan.js",
              "content": "<div class=\"mono\"><%= f.name %></div>",
              "updatedAt": "2025-08-15T09:18:32.852Z"
            }
          ]
        }
      ]
    },
    {
      "id": "a-m-pMRSov",
      "name": "Ekey",
      "description": "ekey cde",
      "owner": "Ekeie",
      "visibility": "private",
      "createdAt": "2025-08-15T09:20:11.690Z",
      "files": [],
      "commits": [
        {
          "id": "b_LD033J",
          "message": "Initial commit",
          "timestamp": "2025-08-15T09:20:11.690Z",
          "filesSnapshot": []
        }
      ]
    }
  ]
}